{
  "last_updated": "2026-06-24T19:15:58Z",
  "markets": {
    "US": {
      "name": "美股 S&P 500",
      "symbol": "%5EGSPC",
      "price": 7341.95,
      "change": -23.51,
      "change_pct": -0.32,
      "trend": "neutral",
      "vix": 20.03,
      "fear_greed_index": 17,
      "fear_greed_label": "Extreme Fear"
    },
    "JP": {
      "name": "日股 日經225",
      "symbol": "%5EN225",
      "price": 69788.38,
      "change": -2565.58,
      "change_pct": -3.55,
      "trend": "down"
    },
    "KR": {
      "name": "韓股 KOSPI",
      "symbol": "%5EKS11",
      "price": 8203.84,
      "change": -910.71,
      "change_pct": -9.99,
      "trend": "down"
    },
    "TW": {
      "name": "台股 加權指數",
      "symbol": "^TWII",
      "price": 46043.6,
      "change": -1057.05,
      "change_pct": -2.24,
      "trend": "down"
    }
  }
}